print_ext/__about__.py
print_ext/__init__.py
print_ext/border_dfn.py
print_ext/borders.py
print_ext/card.py
print_ext/context.py
print_ext/context_cvar.py
print_ext/fill.py
print_ext/flex.py
print_ext/hr.py
print_ext/line.py
print_ext/pretty.py
print_ext/pretty_exception.py
print_ext/printer.py
print_ext/printer_util.py
print_ext/progress.py
print_ext/rich.py
print_ext/sgr.py
print_ext/size.py
print_ext/span.py
print_ext/table.py
print_ext/text.py
print_ext/widget.py
print_ext/mixins/__init__.py
print_ext/mixins/flatten.py
print_ext/mixins/memory.py
print_ext/mixins/pickle.py
print_ext/mixins/progress.py
print_ext/mixins/stream.py
print_ext/mixins/tail.py
print_ext/mixins/task_group.py
print_ext-2.1.1.dist-info/METADATA
print_ext-2.1.1.dist-info/WHEEL
print_ext-2.1.1.dist-info/licenses/LICENSE.txt
print_ext-2.1.1.dist-info/RECORD
