Metadata-Version: 2.1
Name: print-ext
Version: 2.1.1
Summary: Extensions to the print function for pretty-printing with a layout engine.
Project-URL: Documentation, https://github.com/aaron-fl/print_ext#readme
Project-URL: Issues, https://github.com/aaron-fl/print_ext/issues
Project-URL: Source, https://github.com/aaron-fl/print_ext
Author-email: Aaron <aaron@framelunch.jp>
License-Expression: MIT
License-File: LICENSE.txt
Classifier: Development Status :: 4 - Beta
Classifier: Programming Language :: Python
Classifier: Programming Language :: Python :: 3.7
Classifier: Programming Language :: Python :: 3.8
Classifier: Programming Language :: Python :: 3.9
Classifier: Programming Language :: Python :: 3.10
Classifier: Programming Language :: Python :: 3.11
Classifier: Programming Language :: Python :: Implementation :: CPython
Classifier: Programming Language :: Python :: Implementation :: PyPy
Requires-Python: >=3.7
Requires-Dist: wcwidth
